expenselm_mcp_server/__init__.py
expenselm_mcp_server/server.py
expenselm_mcp_server-0.3.1.dist-info/METADATA
expenselm_mcp_server-0.3.1.dist-info/WHEEL
expenselm_mcp_server-0.3.1.dist-info/entry_points.txt
expenselm_mcp_server-0.3.1.dist-info/RECORD
