Metadata-Version: 2.4
Name: expenselm-mcp-server
Version: 0.3.1
Summary: ExpenseLM MCP Server
Project-URL: Homepage, https://github.com/expenselm/expenselm-mcp-server
Requires-Python: >=3.12
Requires-Dist: fastmcp>=2.10.6
Requires-Dist: httpx>=0.28.1
